Workbook

Sheet Leeme
A1: Aranay – métricas de Instagram (Panel profesional)
A2: Fuente: capturas del Panel profesional de Instagram enviadas por Melisa el 25/09/2026.
A3: Cuenta_90d y Actividad_horaria: período 'Últimos 90 días'.
A4: Contenido: Visualizaciones = 'Últimos 30 días'; Interacciones = 'Últimos 90 días'. Las ventanas no son iguales:
A5: como la cuenta arrancó a fines de agosto, casi todo el contenido cae en ambas ventanas, pero la tasa es una estimación.
A6: Celdas vacías en Contenido = la pieza no apareció en las capturas (solo se ven los tops), no significa cero.
A7: Actividad_horaria corresponde al día que estaba seleccionado en la captura (lunes).
A8: Ventas_consultas: tabla con datos reales y simulados (ver columna Origen).
A9: Power BI: Obtener datos > Excel > seleccionar las tablas (tb_...).
A11: Ventas_consultas: filas con Origen = Real son los registros cargados por Melisa (sep 2026).
A12: Filas con Origen = Simulado son un escenario inventado para oct–dic 2026. NO son ventas reales: en cualquier publicación indicarlo como 'datos simulados'.
A13: Ventas reales: cobradas a precio amiga = precio transferencia (lista − 10%) − 10% adicional, es decir lista × 0,81.
A14: Los supuestos de la simulación están en la hoja Supuestos_simulacion; los precios en Productos.

Sheet Cuenta_90d
A1: Métrica | B1: Valor | C1: Detalle
A2: Visualizaciones | B2: 8312 | C2: Total 90 días
A3: Visualizaciones – % seguidores | B3: 0.598
A4: Visualizaciones – % no seguidores | B4: 0.402
A5: Espectadores (cuentas únicas) | B5: 1117
A6: Interacciones | B6: 615 | C6: Total 90 días
A7: Interacciones – % seguidores | B7: 0.885
A8: Interacciones – % no seguidores | B8: 0.115
A9: Cuentas que interactuaron | B9: 89
A10: Actividad del perfil | B10: 679 | C10: Visitas + toques en enlace
A11: Visitas al perfil | B11: 612
A12: Toques en el enlace externo | B12: 67 | C12: Enlace a la tienda web
A13: Total de seguidores | B13: 149 | C13: Al 25/09/2026
A16: Formato | B16: % visualizaciones | C16: % interacciones | D16: Visualizaciones | E16: Interacciones | F16: Tasa de interacción
A17: Historias | B17: 0.574 | C17: 0.434 | D17: =B17*$B$2 -> 4771.088 | E17: =C17*$B$6 -> 266.91 | F17: =IF(D17>0,E17/D17,"") -> 0.055943215
A18: Reels | B18: 0.346 | C18: 0.275 | D18: =B18*$B$2 -> 2875.952 | E18: =C18*$B$6 -> 169.125 | F18: =IF(D18>0,E18/D18,"") -> 0.058806614
A19: Publicaciones | B19: 0.08 | C19: 0.291 | D19: =B19*$B$2 -> 664.96 | E19: =C19*$B$6 -> 178.965 | F19: =IF(D19>0,E19/D19,"") -> 0.26913649

Sheet Contenido
A1: ID | B1: Pieza | C1: Producto / tema | D1: Formato | E1: Fecha | F1: Visualizaciones_30d | G1: Interacciones_90d | H1: Tasa_interaccion
A2: 1 | B2: Look chaleco + pantalón negro (puerta) | C2: Chalecos / sastrero | D2: Carrusel | E2: 46284 | F2: 1200 | G2: 64 | H2: =IF(AND(ISNUMBER(F2),ISNUMBER(G2)),G2/F2,"") -> 0.053333333
A3: 2 | B3: Save the date 9.9 | C3: Lanzamiento / institucional | D3: Reel | E3: 46268 | F3: 649 | G3: 28 | H3: =IF(AND(ISNUMBER(F3),ISNUMBER(G3)),G3/F3,"") -> 0.043143297
A4: 3 | B4: 'Look para cada plan' – top encaje halter | C4: Tops de encaje | D4: Historia | E4: 46276 | F4: 444 | G4: 9 | H4: =IF(AND(ISNUMBER(F4),ISNUMBER(G4)),G4/F4,"") -> 0.02027027
A5: 4 | B5: Conjunto blanco con chaleco (calle, noche) | C5: Chalecos / sastrero | D5: Carrusel | E5: 46286 | F5: 415 | G5: 37 | H5: =IF(AND(ISNUMBER(F5),ISNUMBER(G5)),G5/F5,"") -> 0.089156627
A6: 5 | B6: Bodies #SS27 | C6: Bodies | D6: Reel | E6: 46265 | F6: 356 | G6: 37 | H6: =IF(AND(ISNUMBER(F6),ISNUMBER(G6)),G6/F6,"") -> 0.10393258
A7: 6 | B7: Jean azul + musculosa (parque) | C7: Jeans | D7: Reel | F7: 328 | G7: 25 | H7: =IF(AND(ISNUMBER(F7),ISNUMBER(G7)),G7/F7,"") -> 0.076219512
A8: 7 | B8: Chaleco negro (reja) | C8: Chalecos / sastrero | D8: Reel | F8: 325 | G8: 24 | H8: =IF(AND(ISNUMBER(F8),ISNUMBER(G8)),G8/F8,"") -> 0.073846154
A9: 8 | B9: Conjunto Nara beige (silla) | C9: Chalecos / sastrero | D9: Carrusel | F9: 324 | G9: 23 | H9: =IF(AND(ISNUMBER(F9),ISNUMBER(G9)),G9/F9,"") -> 0.070987654
A10: 9 | B10: Musculosas Morley 3 colores | C10: Musculosas Morley | D10: Reel | E10: 46278 | F10: 311 | G10: 37 | H10: =IF(AND(ISNUMBER(F10),ISNUMBER(G10)),G10/F10,"") -> 0.11897106
A11: 10 | B11: Musculosas Morley escote V | C11: Musculosas Morley | D11: Carrusel | F11: 291 | G11: 27 | H11: =IF(AND(ISNUMBER(F11),ISNUMBER(G11)),G11/F11,"") -> 0.092783505
A12: 11 | B12: '¿Se acuerdan que les conté?' (Morley) | C12: Musculosas Morley | D12: Historia | F12: 92 | G12: 7 | H12: =IF(AND(ISNUMBER(F12),ISNUMBER(G12)),G12/F12,"") -> 0.076086957
A13: 12 | B13: Bodies con puntillas, colores clásicos | C13: Bodies | D13: Historia | F13: 87 | H13: =IF(AND(ISNUMBER(F13),ISNUMBER(G13)),G13/F13,"")
A14: 13 | B14: 'Viernes y 3 planes' | C14: Engagement | D14: Historia | F14: 85 | H14: =IF(AND(ISNUMBER(F14),ISNUMBER(G14)),G14/F14,"")
A15: 14 | B15: Musculosas Morley con tazas | C15: Musculosas Morley | D15: Historia | F15: 84 | H15: =IF(AND(ISNUMBER(F15),ISNUMBER(G15)),G15/F15,"")
A16: 15 | B16: '¿Con qué look te quedás?' | C16: Tops de encaje | D16: Historia | F16: 82 | H16: =IF(AND(ISNUMBER(F16),ISNUMBER(G16)),G16/F16,"")
A17: 16 | B17: Tops de encaje – encuesta de color | C17: Tops de encaje | D17: Historia | F17: 82 | H17: =IF(AND(ISNUMBER(F17),ISNUMBER(G17)),G17/F17,"")
A18: 17 | B18: Top negro | C18: Tops de encaje | D18: Historia | F18: 80 | H18: =IF(AND(ISNUMBER(F18),ISNUMBER(G18)),G18/F18,"")
A19: 18 | B19: '¿Qué plan tenés este finde?' | C19: Engagement | D19: Historia | F19: 77 | H19: =IF(AND(ISNUMBER(F19),ISNUMBER(G19)),G19/F19,"")
A20: 19 | B20: Reseña clienta – Morley (More) | C20: Reseñas | D20: Historia | F20: 76 | G20: 8 | H20: =IF(AND(ISNUMBER(F20),ISNUMBER(G20)),G20/F20,"") -> 0.10526316
A21: 20 | B21: 'Para tu salida a la noche' | C21: Tops de encaje | D21: Historia | F21: 72 | H21: =IF(AND(ISNUMBER(F21),ISNUMBER(G21)),G21/F21,"")
A22: 21 | B22: Reseña clienta – Morley (Cande) | C22: Reseñas | D22: Historia | F22: 71 | G22: 7 | H22: =IF(AND(ISNUMBER(F22),ISNUMBER(G22)),G22/F22,"") -> 0.098591549
A23: 22 | B23: Brunch – 10% OFF | C23: Promoción | D23: Historia | F23: 71 | H23: =IF(AND(ISNUMBER(F23),ISNUMBER(G23)),G23/F23,"")
A24: 23 | B24: Cuenta regresiva '6 días' | C24: Lanzamiento / institucional | D24: Historia | F24: 70 | H24: =IF(AND(ISNUMBER(F24),ISNUMBER(G24)),G24/F24,"")
A25: 24 | B25: Save the date 9/9 (historia) | C25: Lanzamiento / institucional | D25: Historia | F25: 69 | H25: =IF(AND(ISNUMBER(F25),ISNUMBER(G25)),G25/F25,"")
A26: 25 | B26: Wide leg negro – últimos talles | C26: Jeans | D26: Historia | F26: 67 | G26: 7 | H26: =IF(AND(ISNUMBER(F26),ISNUMBER(G26)),G26/F26,"") -> 0.10447761
A27: 26 | B27: Remera rayas celeste | C27: Remeras rayadas | D27: Historia | F27: 65 | G27: 6 | H27: =IF(AND(ISNUMBER(F27),ISNUMBER(G27)),G27/F27,"") -> 0.092307692
A28: 27 | B28: Remera rayas marrón | C28: Remeras rayadas | D28: Historia | F28: 65 | G28: 6 | H28: =IF(AND(ISNUMBER(F28),ISNUMBER(G28)),G28/F28,"") -> 0.092307692
A29: 28 | B29: 'Quieren ver lo que se viene' (sastrero) | C29: Chalecos / sastrero | D29: Historia | F29: 64 | G29: 8 | H29: =IF(AND(ISNUMBER(F29),ISNUMBER(G29)),G29/F29,"") -> 0.125
A30: 29 | B30: 'Faltan horas, mañana abrimos' | C30: Lanzamiento / institucional | D30: Historia | F30: 64 | H30: =IF(AND(ISNUMBER(F30),ISNUMBER(G30)),G30/F30,"")
A31: 30 | B31: Conjunto Nara (historia) | C31: Chalecos / sastrero | D31: Historia | F31: 63 | G31: 8 | H31: =IF(AND(ISNUMBER(F31),ISNUMBER(G31)),G31/F31,"") -> 0.12698413
A32: 31 | B32: Pantalones sastreros – 4 modelos | C32: Chalecos / sastrero | D32: Historia | F32: 63 | G32: 8 | H32: =IF(AND(ISNUMBER(F32),ISNUMBER(G32)),G32/F32,"") -> 0.12698413
A33: 32 | B33: 'Activá las notificaciones' | C33: Lanzamiento / institucional | D33: Historia | F33: 63 | H33: =IF(AND(ISNUMBER(F33),ISNUMBER(G33)),G33/F33,"")
A34: 33 | B34: Reseñas wide leg | C34: Reseñas | D34: Historia | F34: 62 | H34: =IF(AND(ISNUMBER(F34),ISNUMBER(G34)),G34/F34,"")
A35: 34 | B35: Cupón 10% OFF 'solo por hoy' | C35: Promoción | D35: Historia | F35: 61 | H35: =IF(AND(ISNUMBER(F35),ISNUMBER(G35)),G35/F35,"")
A36: 35 | B36: Jean azul (parque) – historia | C36: Jeans | D36: Historia | F36: 60 | H36: =IF(AND(ISNUMBER(F36),ISNUMBER(G36)),G36/F36,"")
A37: 36 | B37: 'Estamos agrandando nuestro catálogo' | C37: Lanzamiento / institucional | D37: Historia | F37: 60 | G37: 10 | H37: =IF(AND(ISNUMBER(F37),ISNUMBER(G37)),G37/F37,"") -> 0.16666667
A38: 37 | B38: Coming soon – septiembre 2026 | C38: Lanzamiento / institucional | D38: Reel | G38: 50 | H38: =IF(AND(ISNUMBER(F38),ISNUMBER(G38)),G38/F38,"")
A39: 38 | B39: Denim streetwear moda | C39: Jeans | D39: Reel | G39: 28 | H39: =IF(AND(ISNUMBER(F39),ISNUMBER(G39)),G39/F39,"")
A40: 39 | B40: Jean gris (carrusel) | C40: Jeans | D40: Carrusel | G40: 20 | H40: =IF(AND(ISNUMBER(F40),ISNUMBER(G40)),G40/F40,"")
A41: 40 | B41: Coming soon – jeans | C41: Jeans | D41: Publicación | G41: 17 | H41: =IF(AND(ISNUMBER(F41),ISNUMBER(G41)),G41/F41,"")
A42: 41 | B42: 'Algo nuevo está tomando forma' | C42: Lanzamiento / institucional | D42: Publicación | G42: 16 | H42: =IF(AND(ISNUMBER(F42),ISNUMBER(G42)),G42/F42,"")
A43: 42 | B43: Top marrón con argolla | C43: Tops de encaje | D43: Publicación | G43: 14 | H43: =IF(AND(ISNUMBER(F43),ISNUMBER(G43)),G43/F43,"")
A44: 43 | B44: Jean gris (foto) | C44: Jeans | D44: Publicación | G44: 13 | H44: =IF(AND(ISNUMBER(F44),ISNUMBER(G44)),G44/F44,"")
A45: 44 | B45: Bodies texturados 3 colores | C45: Bodies | D45: Publicación | G45: 13 | H45: =IF(AND(ISNUMBER(F45),ISNUMBER(G45)),G45/F45,"")
A46: 45 | B46: Chaleco negro (puerta) – historia | C46: Chalecos / sastrero | D46: Historia | G46: 9 | H46: =IF(AND(ISNUMBER(F46),ISNUMBER(G46)),G46/F46,"")
A47: 46 | B47: 'A casi una semana del lanzamiento' | C47: Lanzamiento / institucional | D47: Historia | G47: 8 | H47: =IF(AND(ISNUMBER(F47),ISNUMBER(G47)),G47/F47,"")
A48: 47 | B48: Coming soon – historia | C48: Lanzamiento / institucional | D48: Historia | G48: 8 | H48: =IF(AND(ISNUMBER(F48),ISNUMBER(G48)),G48/F48,"")
A49: 48 | B49: 'Mandanos QUIERO por DM' – 10% OFF | C49: Promoción | D49: Historia | G49: 7 | H49: =IF(AND(ISNUMBER(F49),ISNUMBER(G49)),G49/F49,"")
... A53: 52 | B53: Jean gris – historia | C53: Jeans | D53: Historia | G53: 6 | H53: =IF(AND(ISNUMBER(F53),ISNUMBER(G53)),G53/F53,"")

Sheet Actividad_horaria
A1: Día | B1: Hora | C1: Seguidores activos
A2: Lunes | B2: 0:00 | C2: 11
A3: Lunes | B3: 3:00 | C3: 43
A4: Lunes | B4: 6:00 | C4: 64
A5: Lunes | B5: 9:00 | C5: 68
A6: Lunes | B6: 12:00 | C6: 71
A7: Lunes | B7: 15:00 | C7: 73
A8: Lunes | B8: 18:00 | C8: 63
A9: Lunes | B9: 21:00 | C9: 18

Sheet Productos
A1: Producto | B1: Categoría | C1: Precio de lista web ($) | D1: Fuente
A2: Top Musculosa de Morley Escote V con Tazas | B2: Musculosas Morley | C2: 13910 | D2: Tiendanube
A3: Musculosa de Morley Cuello U con Tazas | B3: Musculosas Morley | C3: 13910 | D3: Tiendanube
A4: Jean Wide Leg Clásico | B4: Jeans y denim | C4: 45810 | D4: Tiendanube
A5: Jean Wide Leg Negro Tiro Alto | B5: Jeans y denim | C5: 45810 | D5: Tiendanube
A6: Short Denim Tiro Alto con Flecos | B6: Jeans y denim | C6: 12810 | D6: Tiendanube
A7: Remera Navy | B7: Remeras y musculosas | C7: 15900 | D7: Tiendanube
A8: Remera Roma | B8: Remeras y musculosas | C8: 13200 | D8: Tiendanube
A9: Musculosa Vanesa cuello cuadrado | B9: Remeras y musculosas | C9: 13200 | D9: Tiendanube
A10: Body Aranay | B10: Bodies | C10: 12810 | D10: Tiendanube
A11: Top Oriental de Encaje | B11: Tops | C11: 18310 | D11: Tiendanube
A12: Top Oriental de Lycra | B12: Tops | C12: 13910 | D12: Tiendanube
A13: Top de Encaje con Lazo | B13: Tops | C13: 15100 | D13: Tiendanube
... A19: Pantalón Siena | B19: Sastrero | C19: 24200 | D19: Tiendanube

Sheet Ventas_consultas
A1: Fecha | B1: Hora | C1: Producto | D1: Categoría | E1: Canal | F1: Tipo | G1: Cantidad | H1: Precio unitario ($) | I1: Monto ($) | J1: Medio de pago | K1: Origen | L1: Mes | M1: MesNum
A2: 46277 | C2: Musculosa de Morley Cuello U con Tazas | D2: Musculosas Morley | E2: Instagram DM | F2: Venta | G2: 1 | H2: 11267 | I2: 11267 | J2: Transferencia | K2: Real | L2: Septiembre | M2: 9
A3: 46290 | C3: Jean Wide Leg Clásico | D3: Jeans y denim | E3: Instagram DM | F3: Venta | G3: 1 | H3: 37106 | I3: 37106 | J3: Transferencia | K3: Real | L3: Septiembre | M3: 9
A4: 46290 | C4: Remera Navy | D4: Remeras y musculosas | E4: Instagram DM | F4: Consulta | G4: 2 | H4: 15900 | I4: 0 | K4: Real | L4: Septiembre | M4: 9
A5: 46290 | C5: Musculosa de Morley Cuello U con Tazas | D5: Musculosas Morley | E5: Instagram DM | F5: Consulta | G5: 1 | H5: 13910 | I5: 0 | K5: Real | L5: Septiembre | M5: 9
A6: 46296 | B6: 08:04 | C6: Musculosa de Morley Cuello U con Tazas | D6: Musculosas Morley | E6: Instagram DM | F6: Consulta | G6: 1 | H6: 13910 | I6: =IF(F6="Venta",G6*H6,0) -> 0 | K6: Simulado | L6: Octubre | M6: 10
A7: 46296 | B7: 11:40 | C7: Top de Encaje con Lazo | D7: Tops | E7: Instagram DM | F7: Venta | G7: 2 | H7: 13590 | I7: =IF(F7="Venta",G7*H7,0) -> 27180 | J7: Transferencia | K7: Simulado | L7: Octubre | M7: 10
A8: 46296 | B8: 16:26 | C8: Top de Encaje con Lazo | D8: Tops | E8: Instagram DM | F8: Consulta | G8: 1 | H8: 15100 | I8: =IF(F8="Venta",G8*H8,0) -> 0 | K8: Simulado | L8: Octubre | M8: 10
A9: 46296 | B9: 17:43 | C9: Jean Wide Leg Clásico | D9: Jeans y denim | E9: Comentario | F9: Consulta | G9: 1 | H9: 45810 | I9: =IF(F9="Venta",G9*H9,0) -> 0 | K9: Simulado | L9: Octubre | M9: 10
A10: 46297 | B10: 11:29 | C10: Top Musculosa de Morley Escote V con Tazas | D10: Musculosas Morley | E10: WhatsApp | F10: Consulta | G10: 1 | H10: 13910 | I10: =IF(F10="Venta",G10*H10,0) -> 0 | K10: Simulado | L10: Octubre | M10: 10
A11: 46297 | B11: 18:11 | C11: Musculosa de Morley Cuello U con Tazas | D11: Musculosas Morley | E11: WhatsApp | F11: Consulta | G11: 1 | H11: 13910 | I11: =IF(F11="Venta",G11*H11,0) -> 0 | K11: Simulado | L11: Octubre | M11: 10
A12: 46297 | B12: 18:26 | C12: Remera Roma | D12: Remeras y musculosas | E12: Instagram DM | F12: Consulta | G12: 1 | H12: 13200 | I12: =IF(F12="Venta",G12*H12,0) -> 0 | K12: Simulado | L12: Octubre | M12: 10
A13: 46298 | B13: 09:34 | C13: Jean Wide Leg Clásico | D13: Jeans y denim | E13: WhatsApp | F13: Venta | G13: 1 | H13: 41229 | I13: =IF(F13="Venta",G13*H13,0) -> 41229 | J13: Transferencia | K13: Simulado | L13: Octubre | M13: 10
A14: 46298 | B14: 22:01 | C14: Musculosa de Morley Cuello U con Tazas | D14: Musculosas Morley | E14: Instagram DM | F14: Venta | G14: 1 | H14: 13910 | I14: =IF(F14="Venta",G14*H14,0) -> 13910 | J14: Mercado Pago | K14: Simulado | L14: Octubre | M14: 10
A15: 46299 | B15: 08:55 | C15: Jean Wide Leg Negro Tiro Alto | D15: Jeans y denim | E15: Instagram DM | F15: Consulta | G15: 1 | H15: 45810 | I15: =IF(F15="Venta",G15*H15,0) -> 0 | K15: Simulado | L15: Octubre | M15: 10
A16: 46299 | B16: 16:22 | C16: Jean Wide Leg Negro Tiro Alto | D16: Jeans y denim | E16: Instagram DM | F16: Venta | G16: 1 | H16: 41229 | I16: =IF(F16="Venta",G16*H16,0) -> 41229 | J16: Transferencia | K16: Simulado | L16: Octubre | M16: 10
A17: 46299 | B17: 16:30 | C17: Body Aranay | D17: Bodies | E17: Instagram DM | F17: Consulta | G17: 1 | H17: 12810 | I17: =IF(F17="Venta",G17*H17,0) -> 0 | K17: Simulado | L17: Octubre | M17: 10
A18: 46300 | B18: 13:32 | C18: Remera Roma | D18: Remeras y musculosas | E18: Web | F18: Venta | G18: 1 | H18: 13200 | I18: =IF(F18="Venta",G18*H18,0) -> 13200 | J18: Mercado Pago | K18: Simulado | L18: Octubre | M18: 10
A19: 46300 | B19: 16:50 | C19: Musculosa Vanesa cuello cuadrado | D19: Remeras y musculosas | E19: Comentario | F19: Consulta | G19: 1 | H19: 13200 | I19: =IF(F19="Venta",G19*H19,0) -> 0 | K19: Simulado | L19: Octubre | M19: 10
A20: 46300 | B20: 17:29 | C20: Top Musculosa de Morley Escote V con Tazas | D20: Musculosas Morley | E20: Instagram DM | F20: Venta | G20: 1 | H20: 12519 | I20: =IF(F20="Venta",G20*H20,0) -> 12519 | J20: Transferencia | K20: Simulado | L20: Octubre | M20: 10
A21: 46302 | B21: 14:17 | C21: Musculosa Vanesa cuello cuadrado | D21: Remeras y musculosas | E21: Instagram DM | F21: Venta | G21: 1 | H21: 11880 | I21: =IF(F21="Venta",G21*H21,0) -> 11880 | J21: Transferencia | K21: Simulado | L21: Octubre | M21: 10
A22: 46302 | B22: 16:20 | C22: Pantalon Gala Recto | D22: Sastrero | E22: Instagram DM | F22: Consulta | G22: 1 | H22: 27000 | I22: =IF(F22="Venta",G22*H22,0) -> 0 | K22: Simulado | L22: Octubre | M22: 10
A23: 46302 | B23: 19:19 | C23: Jean Wide Leg Clásico | D23: Jeans y denim | E23: Instagram DM | F23: Consulta | G23: 1 | H23: 45810 | I23: =IF(F23="Venta",G23*H23,0) -> 0 | K23: Simulado | L23: Octubre | M23: 10
A24: 46303 | B24: 11:54 | C24: Chaleco Gala | D24: Sastrero | E24: Instagram DM | F24: Consulta | G24: 1 | H24: 19900 | I24: =IF(F24="Venta",G24*H24,0) -> 0 | K24: Simulado | L24: Octubre | M24: 10
A25: 46303 | B25: 17:23 | C25: Remera Roma | D25: Remeras y musculosas | E25: Instagram DM | F25: Consulta | G25: 1 | H25: 13200 | I25: =IF(F25="Venta",G25*H25,0) -> 0 | K25: Simulado | L25: Octubre | M25: 10
A26: 46305 | B26: 21:16 | C26: Pantalón Siena | D26: Sastrero | E26: Comentario | F26: Consulta | G26: 1 | H26: 24200 | I26: =IF(F26="Venta",G26*H26,0) -> 0 | K26: Simulado | L26: Octubre | M26: 10
A27: 46306 | B27: 16:39 | C27: Chaleco Nara | D27: Sastrero | E27: Instagram DM | F27: Consulta | G27: 1 | H27: 22000 | I27: =IF(F27="Venta",G27*H27,0) -> 0 | K27: Simulado | L27: Octubre | M27: 10
A28: 46307 | B28: 16:25 | C28: Jean Wide Leg Negro Tiro Alto | D28: Jeans y denim | E28: Instagram DM | F28: Consulta | G28: 1 | H28: 45810 | I28: =IF(F28="Venta",G28*H28,0) -> 0 | K28: Simulado | L28: Octubre | M28: 10
A29: 46307 | B29: 18:44 | C29: Jean Wide Leg Clásico | D29: Jeans y denim | E29: WhatsApp | F29: Consulta | G29: 1 | H29: 45810 | I29: =IF(F29="Venta",G29*H29,0) -> 0 | K29: Simulado | L29: Octubre | M29: 10
A30: 46308 | B30: 10:40 | C30: Chaleco Gala | D30: Sastrero | E30: Instagram DM | F30: Consulta | G30: 1 | H30: 19900 | I30: =IF(F30="Venta",G30*H30,0) -> 0 | K30: Simulado | L30: Octubre | M30: 10
A31: 46308 | B31: 13:02 | C31: Jean Wide Leg Clásico | D31: Jeans y denim | E31: Instagram DM | F31: Consulta | G31: 1 | H31: 45810 | I31: =IF(F31="Venta",G31*H31,0) -> 0 | K31: Simulado | L31: Octubre | M31: 10
A32: 46308 | B32: 13:29 | C32: Musculosa de Morley Cuello U con Tazas | D32: Musculosas Morley | E32: Instagram DM | F32: Consulta | G32: 1 | H32: 13910 | I32: =IF(F32="Venta",G32*H32,0) -> 0 | K32: Simulado | L32: Octubre | M32: 10
A33: 46308 | B33: 20:06 | C33: Chaleco Gala | D33: Sastrero | E33: Instagram DM | F33: Venta | G33: 1 | H33: 17910 | I33: =IF(F33="Venta",G33*H33,0) -> 17910 | J33: Transferencia | K33: Simulado | L33: Octubre | M33: 10
A34: 46309 | B34: 14:43 | C34: Top Oriental de Encaje | D34: Tops | E34: Instagram DM | F34: Consulta | G34: 1 | H34: 18310 | I34: =IF(F34="Venta",G34*H34,0) -> 0 | K34: Simulado | L34: Octubre | M34: 10
A35: 46310 | B35: 16:30 | C35: Top de Encaje con Lazo | D35: Tops | E35: Instagram DM | F35: Consulta | G35: 1 | H35: 15100 | I35: =IF(F35="Venta",G35*H35,0) -> 0 | K35: Simulado | L35: Octubre | M35: 10
A36: 46311 | B36: 13:54 | C36: Top Musculosa de Morley Escote V con Tazas | D36: Musculosas Morley | E36: Instagram DM | F36: Consulta | G36: 1 | H36: 13910 | I36: =IF(F36="Venta",G36*H36,0) -> 0 | K36: Simulado | L36: Octubre | M36: 10
A37: 46311 | B37: 17:07 | C37: Top de Encaje con Lazo | D37: Tops | E37: Instagram DM | F37: Venta | G37: 1 | H37: 13590 | I37: =IF(F37="Venta",G37*H37,0) -> 13590 | J37: Transferencia | K37: Simulado | L37: Octubre | M37: 10
A38: 46311 | B38: 23:18 | C38: Musculosa de Morley Cuello U con Tazas | D38: Musculosas Morley | E38: WhatsApp | F38: Consulta | G38: 1 | H38: 13910 | I38: =IF(F38="Venta",G38*H38,0) -> 0 | K38: Simulado | L38: Octubre | M38: 10
A39: 46312 | B39: 22:06 | C39: Top Musculosa de Morley Escote V con Tazas | D39: Musculosas Morley | E39: Instagram DM | F39: Consulta | G39: 1 | H39: 13910 | I39: =IF(F39="Venta",G39*H39,0) -> 0 | K39: Simulado | L39: Octubre | M39: 10
A40: 46313 | B40: 13:56 | C40: Top Musculosa de Morley Escote V con Tazas | D40: Musculosas Morley | E40: Instagram DM | F40: Consulta | G40: 1 | H40: 13910 | I40: =IF(F40="Venta",G40*H40,0) -> 0 | K40: Simulado | L40: Octubre | M40: 10
A41: 46313 | B41: 15:22 | C41: Pantalón Gala | D41: Sastrero | E41: Instagram DM | F41: Consulta | G41: 1 | H41: 28000 | I41: =IF(F41="Venta",G41*H41,0) -> 0 | K41: Simulado | L41: Octubre | M41: 10
A42: 46313 | B42: 15:33 | C42: Musculosa de Morley Cuello U con Tazas | D42: Musculosas Morley | E42: Instagram DM | F42: Venta | G42: 1 | H42: 12519 | I42: =IF(F42="Venta",G42*H42,0) -> 12519 | J42: Transferencia | K42: Simulado | L42: Octubre | M42: 10
A43: 46313 | B43: 16:09 | C43: Jean Wide Leg Negro Tiro Alto | D43: Jeans y denim | E43: Instagram DM | F43: Consulta | G43: 1 | H43: 45810 | I43: =IF(F43="Venta",G43*H43,0) -> 0 | K43: Simulado | L43: Octubre | M43: 10
A44: 46313 | B44: 16:22 | C44: Musculosa de Morley Cuello U con Tazas | D44: Musculosas Morley | E44: Comentario | F44: Consulta | G44: 1 | H44: 13910 | I44: =IF(F44="Venta",G44*H44,0) -> 0 | K44: Simulado | L44: Octubre | M44: 10
A45: 46313 | B45: 17:09 | C45: Remera Navy | D45: Remeras y musculosas | E45: Instagram DM | F45: Consulta | G45: 1 | H45: 15900 | I45: =IF(F45="Venta",G45*H45,0) -> 0 | K45: Simulado | L45: Octubre | M45: 10
A46: 46314 | B46: 19:52 | C46: Remera Roma | D46: Remeras y musculosas | E46: Instagram DM | F46: Consulta | G46: 1 | H46: 13200 | I46: =IF(F46="Venta",G46*H46,0) -> 0 | K46: Simulado | L46: Octubre | M46: 10
A47: 46315 | B47: 09:17 | C47: Top Musculosa de Morley Escote V con Tazas | D47: Musculosas Morley | E47: Instagram DM | F47: Consulta | G47: 1 | H47: 13910 | I47: =IF(F47="Venta",G47*H47,0) -> 0 | K47: Simulado | L47: Octubre | M47: 10
A48: 46315 | B48: 13:27 | C48: Top Musculosa de Morley Escote V con Tazas | D48: Musculosas Morley | E48: Instagram DM | F48: Venta | G48: 1 | H48: 13910 | I48: =IF(F48="Venta",G48*H48,0) -> 13910 | J48: Mercado Pago | K48: Simulado | L48: Octubre | M48: 10
A49: 46315 | B49: 13:43 | C49: Musculosa de Morley Cuello U con Tazas | D49: Musculosas Morley | E49: Instagram DM | F49: Consulta | G49: 1 | H49: 13910 | I49: =IF(F49="Venta",G49*H49,0) -> 0 | K49: Simulado | L49: Octubre | M49: 10
A50: 46315 | B50: 14:10 | C50: Pantalón Nara | D50: Sastrero | E50: Comentario | F50: Consulta | G50: 1 | H50: 28000 | I50: =IF(F50="Venta",G50*H50,0) -> 0 | K50: Simulado | L50: Octubre | M50: 10
A51: 46315 | B51: 14:56 | C51: Top Musculosa de Morley Escote V con Tazas | D51: Musculosas Morley | E51: Instagram DM | F51: Consulta | G51: 1 | H51: 13910 | I51: =IF(F51="Venta",G51*H51,0) -> 0 | K51: Simulado | L51: Octubre | M51: 10
A52: 46315 | B52: 15:59 | C52: Top Musculosa de Morley Escote V con Tazas | D52: Musculosas Morley | E52: Instagram DM | F52: Venta | G52: 1 | H52: 12519 | I52: =IF(F52="Venta",G52*H52,0) -> 12519 | J52: Transferencia | K52: Simulado | L52: Octubre | M52: 10
A53: 46315 | B53: 17:49 | C53: Top Musculosa de Morley Escote V con Tazas | D53: Musculosas Morley | E53: WhatsApp | F53: Venta | G53: 2 | H53: 12519 | I53: =IF(F53="Venta",G53*H53,0) -> 25038 | J53: Transferencia | K53: Simulado | L53: Octubre | M53: 10
A54: 46316 | B54: 08:29 | C54: Short Denim Tiro Alto con Flecos | D54: Jeans y denim | E54: Web | F54: Venta | G54: 1 | H54: 11529 | I54: =IF(F54="Venta",G54*H54,0) -> 11529 | J54: Transferencia | K54: Simulado | L54: Octubre | M54: 10
A55: 46316 | B55: 13:12 | C55: Short Denim Tiro Alto con Flecos | D55: Jeans y denim | E55: Instagram DM | F55: Consulta | G55: 1 | H55: 12810 | I55: =IF(F55="Venta",G55*H55,0) -> 0 | K55: Simulado | L55: Octubre | M55: 10
A56: 46317 | B56: 11:36 | C56: Short Denim Tiro Alto con Flecos | D56: Jeans y denim | E56: Instagram DM | F56: Consulta | G56: 1 | H56: 12810 | I56: =IF(F56="Venta",G56*H56,0) -> 0 | K56: Simulado | L56: Octubre | M56: 10
A57: 46317 | B57: 11:39 | C57: Jean Wide Leg Negro Tiro Alto | D57: Jeans y denim | E57: Instagram DM | F57: Venta | G57: 1 | H57: 41229 | I57: =IF(F57="Venta",G57*H57,0) -> 41229 | J57: Transferencia | K57: Simulado | L57: Octubre | M57: 10
A58: 46317 | B58: 20:00 | C58: Jean Wide Leg Negro Tiro Alto | D58: Jeans y denim | E58: Instagram DM | F58: Consulta | G58: 1 | H58: 45810 | I58: =IF(F58="Venta",G58*H58,0) -> 0 | K58: Simulado | L58: Octubre | M58: 10
A59: 46318 | B59: 11:41 | C59: Musculosa de Morley Cuello U con Tazas | D59: Musculosas Morley | E59: Instagram DM | F59: Venta | G59: 1 | H59: 12519 | I59: =IF(F59="Venta",G59*H59,0) -> 12519 | J59: Transferencia | K59: Simulado | L59: Octubre | M59: 10
A60: 46318 | B60: 17:16 | C60: Musculosa Vanesa cuello cuadrado | D60: Remeras y musculosas | E60: Instagram DM | F60: Consulta | G60: 1 | H60: 13200 | I60: =IF(F60="Venta",G60*H60,0) -> 0 | K60: Simulado | L60: Octubre | M60: 10
A61: 46320 | B61: 09:55 | C61: Remera Roma | D61: Remeras y musculosas | E61: Instagram DM | F61: Consulta | G61: 1 | H61: 13200 | I61: =IF(F61="Venta",G61*H61,0) -> 0 | K61: Simulado | L61: Octubre | M61: 10
A62: 46320 | B62: 16:54 | C62: Pantalón Gala | D62: Sastrero | E62: Instagram DM | F62: Consulta | G62: 1 | H62: 28000 | I62: =IF(F62="Venta",G62*H62,0) -> 0 | K62: Simulado | L62: Octubre | M62: 10
A63: 46321 | B63: 12:10 | C63: Musculosa de Morley Cuello U con Tazas | D63: Musculosas Morley | E63: Comentario | F63: Consulta | G63: 1 | H63: 13910 | I63: =IF(F63="Venta",G63*H63,0) -> 0 | K63: Simulado | L63: Octubre | M63: 10
A64: 46322 | B64: 18:51 | C64: Remera Navy | D64: Remeras y musculosas | E64: Instagram DM | F64: Consulta | G64: 1 | H64: 15900 | I64: =IF(F64="Venta",G64*H64,0) -> 0 | K64: Simulado | L64: Octubre | M64: 10
A65: 46323 | B65: 11:40 | C65: Jean Wide Leg Clásico | D65: Jeans y denim | E65: Instagram DM | F65: Consulta | G65: 1 | H65: 45810 | I65: =IF(F65="Venta",G65*H65,0) -> 0 | K65: Simulado | L65: Octubre | M65: 10
A66: 46323 | B66: 14:54 | C66: Remera Roma | D66: Remeras y musculosas | E66: Instagram DM | F66: Consulta | G66: 1 | H66: 13200 | I66: =IF(F66="Venta",G66*H66,0) -> 0 | K66: Simulado | L66: Octubre | M66: 10
A67: 46323 | B67: 20:26 | C67: Musculosa de Morley Cuello U con Tazas | D67: Musculosas Morley | E67: WhatsApp | F67: Consulta | G67: 1 | H67: 13910 | I67: =IF(F67="Venta",G67*H67,0) -> 0 | K67: Simulado | L67: Octubre | M67: 10
A68: 46323 | B68: 21:32 | C68: Chaleco Nara | D68: Sastrero | E68: Instagram DM | F68: Consulta | G68: 1 | H68: 22000 | I68: =IF(F68="Venta",G68*H68,0) -> 0 | K68: Simulado | L68: Octubre | M68: 10
A69: 46324 | B69: 16:07 | C69: Top Musculosa de Morley Escote V con Tazas | D69: Musculosas Morley | E69: Instagram DM | F69: Consulta | G69: 1 | H69: 13910 | I69: =IF(F69="Venta",G69*H69,0) -> 0 | K69: Simulado | L69: Octubre | M69: 10
A70: 46324 | B70: 17:35 | C70: Top Oriental de Encaje | D70: Tops | E70: Instagram DM | F70: Consulta | G70: 1 | H70: 18310 | I70: =IF(F70="Venta",G70*H70,0) -> 0 | K70: Simulado | L70: Octubre | M70: 10
A71: 46325 | B71: 09:40 | C71: Body Aranay | D71: Bodies | E71: WhatsApp | F71: Consulta | G71: 1 | H71: 12810 | I71: =IF(F71="Venta",G71*H71,0) -> 0 | K71: Simulado | L71: Octubre | M71: 10
... A73: 46325 | B73: 18:40 | C73: Pantalón Gala | D73: Sastrero | E73: Instagram DM | F73: Consulta | G73: 1 | H73: 28000 | I73: =IF(F73="Venta",G73*H73,0) -> 0 | K73: Simulado | L73: Octubre | M73: 10
A74: 46326 | B74: 08:41 | C74: Top Oriental de Encaje | D74: Tops | E74: Web | F74: Venta | G74: 1 | H74: 18310 | I74: =IF(F74="Venta",G74*H74,0) -> 18310 | J74: Mercado Pago | K74: Simulado | L74: Octubre | M74: 10
A75: 46326 | B75: 14:46 | C75: Short Denim Tiro Alto con Flecos | D75: Jeans y denim | E75: Instagram DM | F75: Consulta | G75: 1 | H75: 12810 | I75: =IF(F75="Venta",G75*H75,0) -> 0 | K75: Simulado | L75: Octubre | M75: 10
A76: 46326 | B76: 20:29 | C76: Top Oriental de Encaje | D76: Tops | E76: Comentario | F76: Consulta | G76: 1 | H76: 18310 | I76: =IF(F76="Venta",G76*H76,0) -> 0 | K76: Simulado | L76: Octubre | M76: 10
A77: 46327 | B77: 12:48 | C77: Body Aranay | D77: Bodies | E77: Instagram DM | F77: Consulta | G77: 1 | H77: 12810 | I77: =IF(F77="Venta",G77*H77,0) -> 0 | K77: Simulado | L77: Noviembre | M77: 11
A78: 46327 | B78: 13:08 | C78: Top Oriental de Lycra | D78: Tops | E78: WhatsApp | F78: Consulta | G78: 1 | H78: 13910 | I78: =IF(F78="Venta",G78*H78,0) -> 0 | K78: Simulado | L78: Noviembre | M78: 11
A79: 46327 | B79: 15:26 | C79: Jean Wide Leg Negro Tiro Alto | D79: Jeans y denim | E79: Instagram DM | F79: Consulta | G79: 1 | H79: 45810 | I79: =IF(F79="Venta",G79*H79,0) -> 0 | K79: Simulado | L79: Noviembre | M79: 11
A80: 46327 | B80: 19:36 | C80: Top Musculosa de Morley Escote V con Tazas | D80: Musculosas Morley | E80: Instagram DM | F80: Venta | G80: 1 | H80: 12519 | I80: =IF(F80="Venta",G80*H80,0) -> 12519 | J80: Transferencia | K80: Simulado | L80: Noviembre | M80: 11
A81: 46328 | B81: 16:23 | C81: Jean Wide Leg Clásico | D81: Jeans y denim | E81: Instagram DM | F81: Consulta | G81: 1 | H81: 45810 | I81: =IF(F81="Venta",G81*H81,0) -> 0 | K81: Simulado | L81: Noviembre | M81: 11
A82: 46328 | B82: 17:43 | C82: Top Oriental de Lycra | D82: Tops | E82: WhatsApp | F82: Venta | G82: 2 | H82: 12519 | I82: =IF(F82="Venta",G82*H82,0) -> 25038 | J82: Transferencia | K82: Simulado | L82: Noviembre | M82: 11
A83: 46328 | B83: 18:42 | C83: Short Denim Tiro Alto con Flecos | D83: Jeans y denim | E83: Instagram DM | F83: Consulta | G83: 1 | H83: 12810 | I83: =IF(F83="Venta",G83*H83,0) -> 0 | K83: Simulado | L83: Noviembre | M83: 11
A84: 46329 | B84: 16:29 | C84: Body Aranay | D84: Bodies | E84: Instagram DM | F84: Venta | G84: 1 | H84: 11529 | I84: =IF(F84="Venta",G84*H84,0) -> 11529 | J84: Transferencia | K84: Simulado | L84: Noviembre | M84: 11
A85: 46329 | B85: 16:59 | C85: Body Aranay | D85: Bodies | E85: Instagram DM | F85: Consulta | G85: 1 | H85: 12810 | I85: =IF(F85="Venta",G85*H85,0) -> 0 | K85: Simulado | L85: Noviembre | M85: 11
A86: 46330 | B86: 12:40 | C86: Jean Wide Leg Negro Tiro Alto | D86: Jeans y denim | E86: Instagram DM | F86: Consulta | G86: 1 | H86: 45810 | I86: =IF(F86="Venta",G86*H86,0) -> 0 | K86: Simulado | L86: Noviembre | M86: 11
A87: 46330 | B87: 13:28 | C87: Jean Wide Leg Negro Tiro Alto | D87: Jeans y denim | E87: WhatsApp | F87: Consulta | G87: 1 | H87: 45810 | I87: =IF(F87="Venta",G87*H87,0) -> 0 | K87: Simulado | L87: Noviembre | M87: 11
A88: 46330 | B88: 18:32 | C88: Short Denim Tiro Alto con Flecos | D88: Jeans y denim | E88: Instagram DM | F88: Venta | G88: 2 | H88: 12810 | I88: =IF(F88="Venta",G88*H88,0) -> 25620 | J88: Mercado Pago | K88: Simulado | L88: Noviembre | M88: 11
A89: 46332 | B89: 16:57 | C89: Jean Wide Leg Clásico | D89: Jeans y denim | E89: Instagram DM | F89: Consulta | G89: 1 | H89: 45810 | I89: =IF(F89="Venta",G89*H89,0) -> 0 | K89: Simulado | L89: Noviembre | M89: 11
A90: 46333 | B90: 08:28 | C90: Musculosa Vanesa cuello cuadrado | D90: Remeras y musculosas | E90: Instagram DM | F90: Consulta | G90: 1 | H90: 13200 | I90: =IF(F90="Venta",G90*H90,0) -> 0 | K90: Simulado | L90: Noviembre | M90: 11
A91: 46333 | B91: 14:06 | C91: Pantalón Nara | D91: Sastrero | E91: Instagram DM | F91: Consulta | G91: 1 | H91: 28000 | I91: =IF(F91="Venta",G91*H91,0) -> 0 | K91: Simulado | L91: Noviembre | M91: 11
A92: 46333 | B92: 14:08 | C92: Remera Navy | D92: Remeras y musculosas | E92: WhatsApp | F92: Consulta | G92: 1 | H92: 15900 | I92: =IF(F92="Venta",G92*H92,0) -> 0 | K92: Simulado | L92: Noviembre | M92: 11
A93: 46334 | B93: 08:42 | C93: Short Denim Tiro Alto con Flecos | D93: Jeans y denim | E93: Comentario | F93: Consulta | G93: 1 | H93: 12810 | I93: =IF(F93="Venta",G93*H93,0) -> 0 | K93: Simulado | L93: Noviembre | M93: 11
A94: 46334 | B94: 15:15 | C94: Top Oriental de Encaje | D94: Tops | E94: Instagram DM | F94: Consulta | G94: 1 | H94: 18310 | I94: =IF(F94="Venta",G94*H94,0) -> 0 | K94: Simulado | L94: Noviembre | M94: 11
A95: 46335 | B95: 11:57 | C95: Jean Wide Leg Clásico | D95: Jeans y denim | E95: WhatsApp | F95: Consulta | G95: 1 | H95: 45810 | I95: =IF(F95="Venta",G95*H95,0) -> 0 | K95: Simulado | L95: Noviembre | M95: 11
A96: 46335 | B96: 13:15 | C96: Pantalon Gala Recto | D96: Sastrero | E96: WhatsApp | F96: Consulta | G96: 1 | H96: 27000 | I96: =IF(F96="Venta",G96*H96,0) -> 0 | K96: Simulado | L96: Noviembre | M96: 11
A97: 46335 | B97: 18:26 | C97: Pantalón Siena | D97: Sastrero | E97: Instagram DM | F97: Consulta | G97: 1 | H97: 24200 | I97: =IF(F97="Venta",G97*H97,0) -> 0 | K97: Simulado | L97: Noviembre | M97: 11
A98: 46335 | B98: 22:40 | C98: Jean Wide Leg Clásico | D98: Jeans y denim | E98: Instagram DM | F98: Consulta | G98: 1 | H98: 45810 | I98: =IF(F98="Venta",G98*H98,0) -> 0 | K98: Simulado | L98: Noviembre | M98: 11
A99: 46336 | B99: 08:32 | C99: Jean Wide Leg Clásico | D99: Jeans y denim | E99: Instagram DM | F99: Venta | G99: 1 | H99: 41229 | I99: =IF(F99="Venta",G99*H99,0) -> 41229 | J99: Transferencia | K99: Simulado | L99: Noviembre | M99: 11
A100: 46336 | B100: 13:12 | C100: Jean Wide Leg Negro Tiro Alto | D100: Jeans y denim | E100: Comentario | F100: Consulta | G100: 1 | H100: 45810 | I100: =IF(F100="Venta",G100*H100,0) -> 0 | K100: Simulado | L100: Noviembre | M100: 11
A101: 46336 | B101: 17:07 | C101: Musculosa Vanesa cuello cuadrado | D101: Remeras y musculosas | E101: Instagram DM | F101: Venta | G101: 2 | H101: 13200 | I101: =IF(F101="Venta",G101*H101,0) -> 26400 | J101: Mercado Pago | K101: Simulado | L101: Noviembre | M101: 11
...

Sheet Conversion_producto
A1: Escenario simulado oct–dic 2026 (Origen = Simulado)
A2: Producto | B2: Categoría | C2: Consultas | D2: Ventas | E2: Tasa de conversión | F2: Unidades | G2: Facturación ($) | H2: Ticket promedio ($)
A3: Top Musculosa de Morley Escote V con Tazas | B3: Musculosas Morley | C3: =COUNTIFS(Ventas_consultas!$C$2:$C$251,$A3,Ventas_consultas!$K$2:$K$251,"Simulado",Ventas_consultas!$F$2:$F$251,"Consulta") -> 22 | D3: =COUNTIFS(Ventas_consultas!$C$2:$C$251,$A3,Ventas_consultas!$K$2:$K$251,"Simulado",Ventas_consultas!$F$2:$F$251,"Venta") -> 10 | E3: =IF(C3>0,D3/C3,"") -> 0.45454545 | F3: =SUMIFS(Ventas_consultas!$G$2:$G$251,Ventas_consultas!$C$2:$C$251,$A3,Ventas_consultas!$K$2:$K$251,"Simulado",Ventas_consultas!$F$2:$F$251,"Venta") -> 12 | G3: =SUMIFS(Ventas_consultas!$I$2:$I$251,Ventas_consultas!$C$2:$C$251,$A3,Ventas_consultas!$K$2:$K$251,"Simulado",Ventas_consultas!$F$2:$F$251,"Venta") -> 155792 | H3: =IF(D3>0,G3/D3,"") -> 15579.2
A4: Musculosa de Morley Cuello U con Tazas | B4: Musculosas Morley | C4: =COUNTIFS(Ventas_consultas!$C$2:$C$251,$A4,Ventas_consultas!$K$2:$K$251,"Simulado",Ventas_consultas!$F$2:$F$251,"Consulta") -> 18 | D4: =COUNTIFS(Ventas_consultas!$C$2:$C$251,$A4,Ventas_consultas!$K$2:$K$251,"Simulado",Ventas_consultas!$F$2:$F$251,"Venta") -> 8 | E4: =IF(C4>0,D4/C4,"") -> 0.44444444 | F4: =SUMIFS(Ventas_consultas!$G$2:$G$251,Ventas_consultas!$C$2:$C$251,$A4,Ventas_consultas!$K$2:$K$251,"Simulado",Ventas_consultas!$F$2:$F$251,"Venta") -> 9 | G4: =SUMIFS(Ventas_consultas!$I$2:$I$251,Ventas_consultas!$C$2:$C$251,$A4,Ventas_consultas!$K$2:$K$251,"Simulado",Ventas_consultas!$F$2:$F$251,"Venta") -> 116844 | H4: =IF(D4>0,G4/D4,"") -> 14605.5
A5: Jean Wide Leg Clásico | B5: Jeans y denim | C5: =COUNTIFS(Ventas_consultas!$C$2:$C$251,$A5,Ventas_consultas!$K$2:$K$251,"Simulado",Ventas_consultas!$F$2:$F$251,"Consulta") -> 20 | D5: =COUNTIFS(Ventas_consultas!$C$2:$C$251,$A5,Ventas_consultas!$K$2:$K$251,"Simulado",Ventas_consultas!$F$2:$F$251,"Venta") -> 7 | E5: =IF(C5>0,D5/C5,"") -> 0.35 | F5: =SUMIFS(Ventas_consultas!$G$2:$G$251,Ventas_consultas!$C$2:$C$251,$A5,Ventas_consultas!$K$2:$K$251,"Simulado",Ventas_consultas!$F$2:$F$251,"Venta") -> 7 | G5: =SUMIFS(Ventas_consultas!$I$2:$I$251,Ventas_consultas!$C$2:$C$251,$A5,Ventas_consultas!$K$2:$K$251,"Simulado",Ventas_consultas!$F$2:$F$251,"Venta") -> 293184 | H5: =IF(D5>0,G5/D5,"") -> 41883.429
A6: Jean Wide Leg Negro Tiro Alto | B6: Jeans y denim | C6: =COUNTIFS(Ventas_consultas!$C$2:$C$251,$A6,Ventas_consultas!$K$2:$K$251,"Simulado",Ventas_consultas!$F$2:$F$251,"Consulta") -> 17 | D6: =COUNTIFS(Ventas_consultas!$C$2:$C$251,$A6,Ventas_consultas!$K$2:$K$251,"Simulado",Ventas_consultas!$F$2:$F$251,"Venta") -> 6 | E6: =IF(C6>0,D6/C6,"") -> 0.35294118 | F6: =SUMIFS(Ventas_consultas!$G$2:$G$251,Ventas_consultas!$C$2:$C$251,$A6,Ventas_consultas!$K$2:$K$251,"Simulado",Ventas_consultas!$F$2:$F$251,"Venta") -> 7 | G6: =SUMIFS(Ventas_consultas!$I$2:$I$251,Ventas_consultas!$C$2:$C$251,$A6,Ventas_consultas!$K$2:$K$251,"Simulado",Ventas_consultas!$F$2:$F$251,"Venta") -> 288603 | H6: =IF(D6>0,G6/D6,"") -> 48100.5
A7: Short Denim Tiro Alto con Flecos | B7: Jeans y denim | C7: =COUNTIFS(Ventas_consultas!$C$2:$C$251,$A7,Ventas_consultas!$K$2:$K$251,"Simulado",Ventas_consultas!$F$2:$F$251,"Consulta") -> 8 | D7: =COUNTIFS(Ventas_consultas!$C$2:$C$251,$A7,Ventas_consultas!$K$2:$K$251,"Simulado",Ventas_consultas!$F$2:$F$251,"Venta") -> 3 | E7: =IF(C7>0,D7/C7,"") -> 0.375 | F7: =SUMIFS(Ventas_consultas!$G$2:$G$251,Ventas_consultas!$C$2:$C$251,$A7,Ventas_consultas!$K$2:$K$251,"Simulado",Ventas_consultas!$F$2:$F$251,"Venta") -> 4 | G7: =SUMIFS(Ventas_consultas!$I$2:$I$251,Ventas_consultas!$C$2:$C$251,$A7,Ventas_consultas!$K$2:$K$251,"Simulado",Ventas_consultas!$F$2:$F$251,"Venta") -> 49959 | H7: =IF(D7>0,G7/D7,"") -> 16653
A8: Remera Navy | B8: Remeras y musculosas | C8: =COUNTIFS(Ventas_consultas!$C$2:$C$251,$A8,Ventas_consultas!$K$2:$K$251,"Simulado",Ventas_consultas!$F$2:$F$251,"Consulta") -> 10 | D8: =COUNTIFS(Ventas_consultas!$C$2:$C$251,$A8,Ventas_consultas!$K$2:$K$251,"Simulado",Ventas_consultas!$F$2:$F$251,"Venta") -> 4 | E8: =IF(C8>0,D8/C8,"") -> 0.4 | F8: =SUMIFS(Ventas_consultas!$G$2:$G$251,Ventas_consultas!$C$2:$C$251,$A8,Ventas_consultas!$K$2:$K$251,"Simulado",Ventas_consultas!$F$2:$F$251,"Venta") -> 4 | G8: =SUMIFS(Ventas_consultas!$I$2:$I$251,Ventas_consultas!$C$2:$C$251,$A8,Ventas_consultas!$K$2:$K$251,"Simulado",Ventas_consultas!$F$2:$F$251,"Venta") -> 60420 | H8: =IF(D8>0,G8/D8,"") -> 15105
A9: Remera Roma | B9: Remeras y musculosas | C9: =COUNTIFS(Ventas_consultas!$C$2:$C$251,$A9,Ventas_consultas!$K$2:$K$251,"Simulado",Ventas_consultas!$F$2:$F$251,"Consulta") -> 8 | D9: =COUNTIFS(Ventas_consultas!$C$2:$C$251,$A9,Ventas_consultas!$K$2:$K$251,"Simulado",Ventas_consultas!$F$2:$F$251,"Venta") -> 3 | E9: =IF(C9>0,D9/C9,"") -> 0.375 | F9: =SUMIFS(Ventas_consultas!$G$2:$G$251,Ventas_consultas!$C$2:$C$251,$A9,Ventas_consultas!$K$2:$K$251,"Simulado",Ventas_consultas!$F$2:$F$251,"Venta") -> 3 | G9: =SUMIFS(Ventas_consultas!$I$2:$I$251,Ventas_consultas!$C$2:$C$251,$A9,Ventas_consultas!$K$2:$K$251,"Simulado",Ventas_consultas!$F$2:$F$251,"Venta") -> 36960 | H9: =IF(D9>0,G9/D9,"") -> 12320
A10: Musculosa Vanesa cuello cuadrado | B10: Remeras y musculosas | C10: =COUNTIFS(Ventas_consultas!$C$2:$C$251,$A10,Ventas_consultas!$K$2:$K$251,"Simulado",Ventas_consultas!$F$2:$F$251,"Consulta") -> 8 | D10: =COUNTIFS(Ventas_consultas!$C$2:$C$251,$A10,Ventas_consultas!$K$2:$K$251,"Simulado",Ventas_consultas!$F$2:$F$251,"Venta") -> 3 | E10: =IF(C10>0,D10/C10,"") -> 0.375 | F10: =SUMIFS(Ventas_consultas!$G$2:$G$251,Ventas_consultas!$C$2:$C$251,$A10,Ventas_consultas!$K$2:$K$251,"Simulado",Ventas_consultas!$F$2:$F$251,"Venta") -> 4 | G10: =SUMIFS(Ventas_consultas!$I$2:$I$251,Ventas_consultas!$C$2:$C$251,$A10,Ventas_consultas!$K$2:$K$251,"Simulado",Ventas_consultas!$F$2:$F$251,"Venta") -> 50160 | H10: =IF(D10>0,G10/D10,"") -> 16720
A11: Body Aranay | B11: Bodies | C11: =COUNTIFS(Ventas_consultas!$C$2:$C$251,$A11,Ventas_consultas!$K$2:$K$251,"Simulado",Ventas_consultas!$F$2:$F$251,"Consulta") -> 15 | D11: =COUNTIFS(Ventas_consultas!$C$2:$C$251,$A11,Ventas_consultas!$K$2:$K$251,"Simulado",Ventas_consultas!$F$2:$F$251,"Venta") -> 4 | E11: =IF(C11>0,D11/C11,"") -> 0.26666667 | F11: =SUMIFS(Ventas_consultas!$G$2:$G$251,Ventas_consultas!$C$2:$C$251,$A11,Ventas_consultas!$K$2:$K$251,"Simulado",Ventas_consultas!$F$2:$F$251,"Venta") -> 6 | G11: =SUMIFS(Ventas_consultas!$I$2:$I$251,Ventas_consultas!$C$2:$C$251,$A11,Ventas_consultas!$K$2:$K$251,"Simulado",Ventas_consultas!$F$2:$F$251,"Venta") -> 69174 | H11: =IF(D11>0,G11/D11,"") -> 17293.5
A12: Top Oriental de Encaje | B12: Tops | C12: =COUNTIFS(Ventas_consultas!$C$2:$C$251,$A12,Ventas_consultas!$K$2:$K$251,"Simulado",Ventas_consultas!$F$2:$F$251,"Consulta") -> 8 | D12: =COUNTIFS(Ventas_consultas!$C$2:$C$251,$A12,Ventas_consultas!$K$2:$K$251,"Simulado",Ventas_consultas!$F$2:$F$251,"Venta") -> 2 | E12: =IF(C12>0,D12/C12,"") -> 0.25 | F12: =SUMIFS(Ventas_consultas!$G$2:$G$251,Ventas_consultas!$C$2:$C$251,$A12,Ventas_consultas!$K$2:$K$251,"Simulado",Ventas_consultas!$F$2:$F$251,"Venta") -> 2 | G12: =SUMIFS(Ventas_consultas!$I$2:$I$251,Ventas_consultas!$C$2:$C$251,$A12,Ventas_consultas!$K$2:$K$251,"Simulado",Ventas_consultas!$F$2:$F$251,"Venta") -> 34789 | H12: =IF(D12>0,G12/D12,"") -> 17394.5
A13: Top Oriental de Lycra | B13: Tops | C13: =COUNTIFS(Ventas_consultas!$C$2:$C$251,$A13,Ventas_consultas!$K$2:$K$251,"Simulado",Ventas_consultas!$F$2:$F$251,"Consulta") -> 6 | D13: =COUNTIFS(Ventas_consultas!$C$2:$C$251,$A13,Ventas_consultas!$K$2:$K$251,"Simulado",Ventas_consultas!$F$2:$F$251,"Venta") -> 2 | E13: =IF(C13>0,D13/C13,"") -> 0.33333333 | F13: =SUMIFS(Ventas_consultas!$G$2:$G$251,Ventas_consultas!$C$2:$C$251,$A13,Ventas_consultas!$K$2:$K$251,"Simulado",Ventas_consultas!$F$2:$F$251,"Venta") -> 3 | G13: =SUMIFS(Ventas_consultas!$I$2:$I$251,Ventas_consultas!$C$2:$C$251,$A13,Ventas_consultas!$K$2:$K$251,"Simulado",Ventas_consultas!$F$2:$F$251,"Venta") -> 37557 | H13: =IF(D13>0,G13/D13,"") -> 18778.5
A14: Top de Encaje con Lazo | B14: Tops | C14: =COUNTIFS(Ventas_consultas!$C$2:$C$251,$A14,Ventas_consultas!$K$2:$K$251,"Simulado",Ventas_consultas!$F$2:$F$251,"Consulta") -> 6 | D14: =COUNTIFS(Ventas_consultas!$C$2:$C$251,$A14,Ventas_consultas!$K$2:$K$251,"Simulado",Ventas_consultas!$F$2:$F$251,"Venta") -> 2 | E14: =IF(C14>0,D14/C14,"") -> 0.33333333 | F14: =SUMIFS(Ventas_consultas!$G$2:$G$251,Ventas_consultas!$C$2:$C$251,$A14,Ventas_consultas!$K$2:$K$251,"Simulado",Ventas_consultas!$F$2:$F$251,"Venta") -> 3 | G14: =SUMIFS(Ventas_consultas!$I$2:$I$251,Ventas_consultas!$C$2:$C$251,$A14,Ventas_consultas!$K$2:$K$251,"Simulado",Ventas_consultas!$F$2:$F$251,"Venta") -> 40770 | H14: =IF(D14>0,G14/D14,"") -> 20385
... A20: Pantalón Siena | B20: Sastrero | C20: =COUNTIFS(Ventas_consultas!$C$2:$C$251,$A20,Ventas_consultas!$K$2:$K$251,"Simulado",Ventas_consultas!$F$2:$F$251,"Consulta") -> 7 | D20: =COUNTIFS(Ventas_consultas!$C$2:$C$251,$A20,Ventas_consultas!$K$2:$K$251,"Simulado",Ventas_consultas!$F$2:$F$251,"Venta") -> 1 | E20: =IF(C20>0,D20/C20,"") -> 0.14285714 | F20: =SUMIFS(Ventas_consultas!$G$2:$G$251,Ventas_consultas!$C$2:$C$251,$A20,Ventas_consultas!$K$2:$K$251,"Simulado",Ventas_consultas!$F$2:$F$251,"Venta") -> 1 | G20: =SUMIFS(Ventas_consultas!$I$2:$I$251,Ventas_consultas!$C$2:$C$251,$A20,Ventas_consultas!$K$2:$K$251,"Simulado",Ventas_consultas!$F$2:$F$251,"Venta") -> 21780 | H20: =IF(D20>0,G20/D20,"") -> 21780
A21: Total | C21: =SUM(C3:C20) -> 186 | D21: =SUM(D3:D20) -> 60 | E21: =IF(C21>0,D21/C21,"") -> 0.32258065 | F21: =SUM(F3:F20) -> 71 | G21: =SUM(G3:G20) -> 1395402 | H21: =IF(D21>0,G21/D21,"") -> 23256.7
A23: Datos reales (sep 2026)
A24: Consultas reales | B24: =COUNTIFS(Ventas_consultas!$F$2:$F$251,"Consulta",Ventas_consultas!$K$2:$K$251,"Real") -> 2
A25: Ventas reales | B25: =COUNTIFS(Ventas_consultas!$F$2:$F$251,"Venta",Ventas_consultas!$K$2:$K$251,"Real") -> 2
A26: Facturación real ($) | B26: =SUMIFS(Ventas_consultas!$I$2:$I$251,Ventas_consultas!$F$2:$F$251,"Venta",Ventas_consultas!$K$2:$K$251,"Real") -> 48373

Sheet Embudo
A1: Etapa | B1: Cantidad | C1: % vs etapa anterior | D1: % vs espectadores
A2: Visualizaciones | B2: =Cuenta_90d!B2 -> 8312
A3: Espectadores (cuentas únicas) | B3: =Cuenta_90d!B5 -> 1117 | C3: =IF(B2>0,B3/B2,"") -> 0.13438402
A4: Visitas al perfil | B4: =Cuenta_90d!B11 -> 612 | C4: =IF(B3>0,B4/B3,"") -> 0.54789615 | D4: =IF($B$3>0,B4/$B$3,"") -> 0.54789615
A5: Toques en el enlace a la web | B5: =Cuenta_90d!B12 -> 67 | C5: =IF(B4>0,B5/B4,"") -> 0.10947712 | D5: =IF($B$3>0,B5/$B$3,"") -> 0.059982095
A6: Conversaciones (consultas + ventas) | B6: =COUNTIFS(Ventas_consultas!$K$2:$K$251,"Real") -> 4 | C6: =IF(B5>0,B6/B5,"") -> 0.059701493 | D6: =IF($B$3>0,B6/$B$3,"") -> 0.0035810206
A7: Ventas | B7: =COUNTIFS(Ventas_consultas!$F$2:$F$251,"Venta",Ventas_consultas!$K$2:$K$251,"Real") -> 2 | C7: =IF(B6>0,B7/B6,"") -> 0.5 | D7: =IF($B$3>0,B7/$B$3,"") -> 0.0017905103
A9: Solo datos reales. Las ventas se concretaron por DM y transferencia, no por la web: el paso enlace → conversación no es secuencial.

Sheet Supuestos_simulacion
A1: Producto | B1: Consultas simuladas | C1: Tasa de conversión supuesta | D1: Justificación
A2: Top Musculosa de Morley Escote V con Tazas | B2: 22 | C2: 0.45 | D2: Mejor tasa de interacción en Instagram (≈12%) y producto más consultado real
A3: Musculosa de Morley Cuello U con Tazas | B3: 18 | C3: 0.45 | D3: Mejor tasa de interacción en Instagram (≈12%) y producto más consultado real
A4: Jean Wide Leg Clásico | B4: 20 | C4: 0.35 | D4: Segundo producto más consultado; ya tiene venta real
A5: Jean Wide Leg Negro Tiro Alto | B5: 17 | C5: 0.35 | D5: Segundo producto más consultado; ya tiene venta real
A6: Short Denim Tiro Alto con Flecos | B6: 8 | C6: 0.35 | D6: Segundo producto más consultado; ya tiene venta real
A7: Remera Navy | B7: 10 | C7: 0.4 | D7: Precio bajo, compra de impulso; Remera Navy ya tiene 2 ventas reales
A8: Remera Roma | B8: 8 | C8: 0.4 | D8: Precio bajo, compra de impulso; Remera Navy ya tiene 2 ventas reales
A9: Musculosa Vanesa cuello cuadrado | B9: 8 | C9: 0.4 | D9: Precio bajo, compra de impulso; Remera Navy ya tiene 2 ventas reales
A10: Body Aranay | B10: 15 | C10: 0.3 | D10: Buena tasa de interacción (≈10%)
A11: Top Oriental de Encaje | B11: 8 | C11: 0.25 | D11: Alcance medio en historias
A12: Top Oriental de Lycra | B12: 6 | C12: 0.25 | D12: Alcance medio en historias
A13: Top de Encaje con Lazo | B13: 6 | C13: 0.25 | D13: Alcance medio en historias
... A19: Pantalón Siena | B19: 7 | C19: 0.15 | D19: Mucho alcance (look más visto) pero precio alto: baja conversión
A21: Período simulado: 01/10/2026 a 31/12/2026, con más volumen en diciembre (28% / 32% / 40% por mes).
A22: Cada venta simulada nace de una consulta simulada, 0 a 3 días después.
A23: Horarios ponderados según la actividad real de seguidores (pico 9–18 h).
A24: Canal consultas: 70% DM, 20% WhatsApp, 10% comentario. Canal ventas: 65% DM, 25% WhatsApp, 10% web.
A25: Precio de ventas simuladas: lista web; por transferencia, lista − 10% (política real de Aranay).
A26: Pago: 70% transferencia, 30% Mercado Pago. Cantidad: 85% una unidad, 15% dos.
A27: Semilla aleatoria fija (2026): el dataset es reproducible.
